requests_middleware_ali_hmac.py
requests_middleware_ali_hmac-0.1.3.dist-info/LICENSE
requests_middleware_ali_hmac-0.1.3.dist-info/METADATA
requests_middleware_ali_hmac-0.1.3.dist-info/WHEEL
requests_middleware_ali_hmac-0.1.3.dist-info/top_level.txt
requests_middleware_ali_hmac-0.1.3.dist-info/zip-safe
requests_middleware_ali_hmac-0.1.3.dist-info/RECORD
